llama_index/node_parser/topic/__init__.py
llama_index/node_parser/topic/base.py
llama_index_node_parser_topic-0.3.1.dist-info/METADATA
llama_index_node_parser_topic-0.3.1.dist-info/WHEEL
llama_index_node_parser_topic-0.3.1.dist-info/licenses/LICENSE
llama_index_node_parser_topic-0.3.1.dist-info/RECORD
