Metadata-Version: 2.4
Name: llama-index-node-parser-topic
Version: 0.3.1
Summary: llama-index node_parser topic node parser integration
Author: llama-index
License-Expression: MIT
License-File: LICENSE
Requires-Python: <4.0,>=3.9
Requires-Dist: llama-index-core<0.15,>=0.13.0
